csbuild/__init__.py
csbuild/commands.py
csbuild/log.py
csbuild/perf_timer.py
csbuild/version
csbuild/_build/__init__.py
csbuild/_build/context_manager.py
csbuild/_build/input_file.py
csbuild/_build/project.py
csbuild/_build/project_plan.py
csbuild/_build/recompile.py
csbuild/_testing/__init__.py
csbuild/_testing/functional_test.py
csbuild/_testing/pylint_license_check.py
csbuild/_testing/pylint_test.py
csbuild/_testing/run_pylint.py
csbuild/_testing/run_unit_tests.py
csbuild/_testing/testcase.py
csbuild/_utils/__init__.py
csbuild/_utils/dag.py
csbuild/_utils/decorators.py
csbuild/_utils/ordered_set.py
csbuild/_utils/queue.py
csbuild/_utils/reraise.py
csbuild/_utils/reraise.py2
csbuild/_utils/reraise.py3
csbuild/_utils/response_file.py
csbuild/_utils/settings_manager.py
csbuild/_utils/shared_globals.py
csbuild/_utils/string_abc.py
csbuild/_utils/system.py
csbuild/_utils/terminfo.py
csbuild/_utils/thread_pool.py
csbuild/plugin/__init__.py
csbuild/toolchain/__init__.py
csbuild/toolchain/toolchain.py
csbuild/tools/__init__.py
csbuild/tools/assemblers/__init__.py
csbuild/tools/assemblers/android_clang_assembler.py
csbuild/tools/assemblers/android_gcc_assembler.py
csbuild/tools/assemblers/assembler_base.py
csbuild/tools/assemblers/clang_assembler.py
csbuild/tools/assemblers/gcc_assembler.py
csbuild/tools/assemblers/msvc_assembler.py
csbuild/tools/assemblers/ps3_assembler.py
csbuild/tools/assemblers/ps4_assembler.py
csbuild/tools/assemblers/psvita_assembler.py
csbuild/tools/common/__init__.py
csbuild/tools/common/android_tool_base.py
csbuild/tools/common/apple_tool_base.py
csbuild/tools/common/compiler_flags.py
csbuild/tools/common/java_tool_base.py
csbuild/tools/common/linker_flags.py
csbuild/tools/common/msvc_tool_base.py
csbuild/tools/common/sony_tool_base.py
csbuild/tools/common/tool_traits.py
csbuild/tools/cpp_compilers/__init__.py
csbuild/tools/cpp_compilers/android_clang_cpp_compiler.py
csbuild/tools/cpp_compilers/android_gcc_cpp_compiler.py
csbuild-0.93.1.dist-info/METADATA
csbuild-0.93.1.dist-info/WHEEL
csbuild-0.93.1.dist-info/top_level.txt
csbuild-0.93.1.dist-info/RECORD
